NotYetSelfAware/__init__.py
NotYetSelfAware-0.0.3.dist-info/LICENSE
NotYetSelfAware-0.0.3.dist-info/METADATA
NotYetSelfAware-0.0.3.dist-info/WHEEL
NotYetSelfAware-0.0.3.dist-info/top_level.txt
NotYetSelfAware-0.0.3.dist-info/RECORD
