Metadata-Version: 2.1
Name: NotYetSelfAware
Version: 0.0.3
Summary: My implementation of Neaural Networks
Home-page: https://github.com/ezalos/NotYetSelfAware
Author: ezalos
Author-email: ezalos@gmail.com
License: UNKNOWN
Project-URL: Bug Tracker, https://github.com/ezalos/NotYetSelfAware/issues
Platform: UNKNOWN
Classifier: Programming Language :: Python :: 3
Classifier: License :: OSI Approved :: MIT License
Classifier: Operating System :: OS Independent
Requires-Python: >=3.6
License-File: LICENSE
